domaintypesystem/__init__.py
domaintypesystem/dts.py
domaintypesystem/multicastgroups.py
domaintypesystem/schema/domain_type_group_membership.capnp
domaintypesystem/schema/domain_type_group_message.capnp
domaintypesystem-0.1.9.dist-info/LICENSE.txt
domaintypesystem-0.1.9.dist-info/METADATA
domaintypesystem-0.1.9.dist-info/WHEEL
domaintypesystem-0.1.9.dist-info/entry_points.txt
domaintypesystem-0.1.9.dist-info/top_level.txt
domaintypesystem-0.1.9.dist-info/RECORD
